gentab/__init__.py
gentab/utils.py
gentab/data/__init__.py
gentab/data/config.py
gentab/data/dataset.py
gentab/evaluators/__init__.py
gentab/evaluators/catboost.py
gentab/evaluators/evaluator.py
gentab/evaluators/knn.py
gentab/evaluators/lightgbm.py
gentab/evaluators/mlp.py
gentab/evaluators/xgboost.py
gentab/generators/__init__.py
gentab/generators/adasyn.py
gentab/generators/autodiffusion.py
gentab/generators/copulagan.py
gentab/generators/ctabgan.py
gentab/generators/ctabganplus.py
gentab/generators/ctgan.py
gentab/generators/forestdiffusion.py
gentab/generators/gaussiancopula.py
gentab/generators/generator.py
gentab/generators/great.py
gentab/generators/randomoversampler.py
gentab/generators/smote.py
gentab/generators/tabula.py
gentab/generators/tvae.py
gentab/generators/autodiff/TabDDPMdiff.py
gentab/generators/autodiff/autoencoder.py
gentab/generators/autodiff/diffusion.py
gentab/generators/autodiff/process_GQ.py
gentab/generators/autodiff/process_edited.py
gentab/generators/ctabg/pipeline/data_preparation.py
gentab/generators/ctabg/synthesizer/ctabgan_synthesizer.py
gentab/generators/ctabg/synthesizer/transformer.py
gentab/generators/ctabgplus/pipeline/data_preparation.py
gentab/generators/ctabgplus/privacy_utils/rdp_accountant.py
gentab/generators/ctabgplus/synthesizer/ctabgan_synthesizer.py
gentab/generators/ctabgplus/synthesizer/transformer.py
gentab/generators/dae/__init__.py
gentab/generators/dae/data.py
gentab/generators/dae/engine.py
gentab/generators/dae/model.py
gentab/generators/dae/network.py
gentab/generators/dae/util.py
gentab/generators/tabu/tabula.py
gentab/generators/tabu/tabula_dataset.py
gentab/generators/tabu/tabula_start.py
gentab/generators/tabu/tabula_trainer.py
gentab/generators/tabu/tabula_utils.py
gentab/generators/tabump/tabula.py
gentab/generators/tabump/tabula_dataset.py
gentab/generators/tabump/tabula_start.py
gentab/generators/tabump/tabula_trainer.py
gentab/generators/tabump/tabula_utils.py
gentab/tuners/__init__.py
gentab-0.1.2.dist-info/METADATA
gentab-0.1.2.dist-info/WHEEL
gentab-0.1.2.dist-info/licenses/LICENSE
gentab-0.1.2.dist-info/RECORD
