Metadata-Version: 2.3
Name: gentab
Version: 0.1.2
Summary: A synthetic tabular data generation library.
Project-URL: Homepage, https://github.com/omaralvarez/gentab
Project-URL: Issues, https://github.com/omaralvarez/gentab/issues
Author-email: "Omar A. Mures" <omar.alvarez@udc.es>
License-File: LICENSE
Keywords: data,deep learning,generation,machine learning,synthetic,tabular
Classifier: License :: OSI Approved :: GNU General Public License v3 (GPLv3)
Classifier: Operating System :: OS Independent
Classifier: Programming Language :: Python :: 3
Requires-Python: >=3.9
Requires-Dist: be-great==0.0.7
Requires-Dist: category-encoders==2.6.3
Requires-Dist: dask==2024.1.1
Requires-Dist: datasets==2.15.0
Requires-Dist: dython==0.7.5
Requires-Dist: forestdiffusion==1.0.5
Requires-Dist: humanize==4.9.0
Requires-Dist: imbalanced-learn==0.11.0
Requires-Dist: lightning==2.1.2
Requires-Dist: optuna==3.5.0
Requires-Dist: pandas==2.1.3
Requires-Dist: rich==13.1.0
Requires-Dist: scikit-learn==1.3.2
Requires-Dist: sdv==1.8.0
Requires-Dist: skorch==0.15.0
Requires-Dist: torch==2.0.1
Requires-Dist: torchaudio==2.0.2
Requires-Dist: torchmetrics==1.2.1
Requires-Dist: torchvision==0.15.2
Requires-Dist: transformers==4.38.2
Requires-Dist: ucimlrepo==0.0.3
Provides-Extra: dev
Requires-Dist: black; extra == 'dev'
